arnoldas_a_mod1_atsiskaitymas/__init__.py
arnoldas_a_mod1_atsiskaitymas/book_info.py
arnoldas_a_mod1_atsiskaitymas/crawler.py
arnoldas_a_mod1_atsiskaitymas/football_results.py
samples/__init__.py
tests/__init__.py
tests/test_book_info.py
tests/test_football_results.py
arnoldas_a_mod1_atsiskaitymas-0.1.5.dist-info/METADATA
arnoldas_a_mod1_atsiskaitymas-0.1.5.dist-info/WHEEL
arnoldas_a_mod1_atsiskaitymas-0.1.5.dist-info/top_level.txt
arnoldas_a_mod1_atsiskaitymas-0.1.5.dist-info/RECORD
