Metadata-Version: 2.1
Name: arnoldas-a-mod1-atsiskaitymas
Version: 0.1.5
Summary: A Python project for scraping book info and football results
Home-page: https://github.com/Asasai001/arnoldas-a-mod1-atsiskaitymas
Author: Arnoldas A.
Author-email: ambrasas.arnoldas@gmail.com
Requires-Python: >=3.10
Requires-Dist: selenium
Requires-Dist: pandas
